kiwoomAsync/__init__.py
kiwoomAsync/async_api.py
kiwoomAsync/kf_dispatch.py
kiwoomAsync/kh_dispatch.py
kiwoomAsync/models.py
kiwoomasync-0.0.8.dist-info/METADATA
kiwoomasync-0.0.8.dist-info/WHEEL
kiwoomasync-0.0.8.dist-info/licenses/LICENSE
kiwoomasync-0.0.8.dist-info/RECORD
