Metadata-Version: 2.3
Name: kiwoomAsync
Version: 0.0.8
Summary: package for async kiwoom api
Project-URL: Homepage, https://github.com/teranum/python-packages/tree/master/kiwoomAsync
Author-email: teranum <teranum@gmail.com>
Keywords: kiwoom
Classifier: License :: OSI Approved :: MIT License
Classifier: Operating System :: OS Independent
Classifier: Programming Language :: Python :: 3
Requires-Python: >=3.8
Requires-Dist: pyqt5
Requires-Dist: qasync
